setup.py
superpower/__init__.py
superpower.egg-info/PKG-INFO
superpower.egg-info/SOURCES.txt
superpower.egg-info/dependency_links.txt
superpower.egg-info/not-zip-safe
superpower.egg-info/top_level.txt