Metadata-Version: 1.0
Name: superpower
Version: 0.1
Summary: https://github.com/veitsi/superpower
Home-page: https://github.com/veitsi/superpower
Author: vei tsi
Author-email: flyingcircus@example.com
License: MIT
Platform: UNKNOWN
